LICENSE
MANIFEST.in
README.md
requirements.txt
setup.py
rtac/__init__.py
rtac/rtac.py
rtac.egg-info/PKG-INFO
rtac.egg-info/SOURCES.txt
rtac.egg-info/dependency_links.txt
rtac.egg-info/requires.txt
rtac.egg-info/top_level.txt
rtac/ac_functionalities/__init__.py
rtac/ac_functionalities/config_gens.py
rtac/ac_functionalities/logs.py
rtac/ac_functionalities/result_processing.py
rtac/ac_functionalities/rtac_data.py
rtac/ac_functionalities/ta_runner.py
rtac/ac_functionalities/tournament.py
rtac/ac_functionalities/tournament_manager.py
rtac/ac_functionalities/ranking/__init__.py
rtac/ac_functionalities/ranking/cppl.py
rtac/ac_functionalities/ranking/gray_box.py
rtac/ac_functionalities/ranking/trueskill.py
rtac/data/params_tsp.json
rtac/data/travellingsalesman_instances.txt
rtac/data/tsp_scenario_rt_test.txt
rtac/data/instances/travellingsalesman/instance_10.json
rtac/data/instances/travellingsalesman/instance_100.json
rtac/data/instances/travellingsalesman/instance_11.json
rtac/data/instances/travellingsalesman/instance_12.json
rtac/data/instances/travellingsalesman/instance_13.json
rtac/data/instances/travellingsalesman/instance_14.json
rtac/data/instances/travellingsalesman/instance_15.json
rtac/data/instances/travellingsalesman/instance_16.json
rtac/data/instances/travellingsalesman/instance_17.json
rtac/data/instances/travellingsalesman/instance_18.json
rtac/data/instances/travellingsalesman/instance_19.json
rtac/data/instances/travellingsalesman/instance_20.json
rtac/data/instances/travellingsalesman/instance_21.json
rtac/data/instances/travellingsalesman/instance_22.json
rtac/data/instances/travellingsalesman/instance_23.json
rtac/data/instances/travellingsalesman/instance_24.json
rtac/data/instances/travellingsalesman/instance_25.json
rtac/data/instances/travellingsalesman/instance_26.json
rtac/data/instances/travellingsalesman/instance_27.json
rtac/data/instances/travellingsalesman/instance_28.json
rtac/data/instances/travellingsalesman/instance_29.json
rtac/data/instances/travellingsalesman/instance_3.json
rtac/data/instances/travellingsalesman/instance_30.json
