Metadata-Version: 2.1
Name: rtac
Version: 0.0.1.3
Summary: RTAC is a collection of Realtime Algorithm Configuration methods.
Home-page: https://github.com/DimitriWeiss/RTAC.git
Author: Dimitri Weiß
Author-email: dimitri-weiss@web.de
License: LICENSE
Platform: UNKNOWN
Classifier: Intended Audience :: Science/Research
Classifier: Operating System :: POSIX :: Linux
Classifier: Programming Language :: Python :: 3.10
License-File: LICENSE
